<?xml version="1.0" encoding="UTF-8"?>
<!DOCTYPE mapper PUBLIC "-//mybatis.org//DTD Mapper 3.0//EN"
        "http://mybatis.org/dtd/mybatis-3-mapper.dtd">

<mapper namespace="com.deushu.store.mapper.StoreMapper">

  <!-- 1) 가게 기본 정보 -->
    <select id="findStoreInfo" parameterType="long"
            resultType="com.deushu.store.dto.StoreDetailResponse$StoreInfo">
        SELECT
            s.id,
            s.name,
            s.category,
            s.address,
            s.lat,
            s.lng,
            s.thumbnail_url AS thumbnailUrl,
            CAST(s.open_time AS CHAR)  AS openTime,
            CAST(s.close_time AS CHAR) AS closeTime
        FROM stores s
        WHERE s.id = #{storeId}
    </select>

	  <!-- 2) 가게 이미지 목록 -->
	<select id="findStoreImages" parameterType="long" resultType="string">
    SELECT si.image_url
    FROM store_images si
    WHERE si.store_id = #{storeId}
    ORDER BY si.sort_order ASC, si.created_at ASC
</select>

    <!-- 3) 리뷰 평점/개수 -->
    <select id="findRatingInfo" parameterType="long"
            resultType="com.deushu.store.dto.StoreDetailResponse$RatingInfo">
        SELECT
            COALESCE(ROUND(AVG(r.rating), 1), 0) AS avg,
            COUNT(*) AS count
        FROM reviews r
        WHERE r.store_id = #{storeId}
    </select>

    <!-- 4) 판매중 상품 목록 -->
    <select id="findSellingItems" parameterType="long"
            resultType="com.deushu.store.dto.StoreDetailResponse$ItemInfo">
        SELECT
            i.id,
            i.name,
            i.original_price AS originalPrice,
            i.discount_price AS discountPrice,
            i.discount_rate AS discountRate,
            i.stock,
            i.expire_at AS expireAt,
            i.thumbnail_url AS thumbnailUrl
        FROM items i
        WHERE i.store_id = #{storeId}
          AND i.expire_at > NOW()
          AND i.stock > 0
        ORDER BY i.expire_at ASC
    </select>

    <!-- ══════════════════════════════════════════════════════════════
         공통 ResultMap
    ══════════════════════════════════════════════════════════════ -->
    <resultMap id="StoreMapDtoResultMap" type="com.deushu.store.dto.StoreMapDto">
        <id     property="id"               column="id"/>
        <result property="name"             column="name"/>
        <result property="lat"              column="lat"/>
        <result property="lng"              column="lng"/>
        <result property="category"         column="category"/>
        <result property="closeTime"        column="close_time"/>
        <result property="thumbnailUrl"     column="thumbnail_url"/>
        <result property="totalStock"       column="total_stock"/>
        <result property="minDiscountPrice" column="min_discount_price"/>
        <result property="minOriginalPrice" column="min_original_price"/>
        <result property="maxDiscountRate"  column="max_discount_rate"/>
        <result property="distanceKm"       column="distance_km"/>
    </resultMap>

    <resultMap id="StoreDetailDtoResultMap" type="com.deushu.store.dto.StoreDetailDto">
        <id     property="id"           column="id"/>
        <result property="name"         column="name"/>
        <result property="category"     column="category"/>
        <result property="address"      column="address"/>
        <result property="lat"          column="lat"/>
        <result property="lng"          column="lng"/>
        <result property="openTime"     column="open_time"/>
        <result property="closeTime"    column="close_time"/>
        <result property="thumbnailUrl" column="thumbnail_url"/>
        <result property="favorited"    column="favorited"/>
        <result property="avgRating"    column="avg_rating"/>
        <result property="reviewCount"  column="review_count"/>
    </resultMap>

    <resultMap id="ItemSummaryDtoResultMap" type="com.deushu.store.dto.StoreDetailDto$ItemSummaryDto">
        <id     property="id"            column="id"/>
        <result property="name"          column="name"/>
        <result property="originalPrice" column="original_price"/>
        <result property="discountPrice" column="discount_price"/>
        <result property="discountRate"  column="discount_rate"/>
        <result property="stock"         column="stock"/>
        <result property="expireAt"      column="expire_at"/>
        <result property="thumbnailUrl"  column="thumbnail_url"/>
    </resultMap>

    <!-- ══════════════════════════════════════════════════════════════
         공통 SQL 조각
    ══════════════════════════════════════════════════════════════ -->

    <!-- 하버사인 공식: centerLat/centerLng이 있으면 거리(km) 계산 -->
    <sql id="distanceCalc">
        <choose>
            <when test="centerLat != null and centerLng != null">
                (6371 * ACOS(
                    COS(RADIANS(#{centerLat})) * COS(RADIANS(s.lat)) *
                    COS(RADIANS(s.lng) - RADIANS(#{centerLng})) +
                    SIN(RADIANS(#{centerLat})) * SIN(RADIANS(s.lat))
                ))
            </when>
            <otherwise>
                NULL
            </otherwise>
        </choose>
        AS distance_km
    </sql>

    <!-- 활성 가게 + 활성 상품 기본 조건 -->
    <sql id="baseActiveCondition">
        s.deleted_at IS NULL
        AND i.deleted_at IS NULL
        AND i.stock      > 0
        AND i.expire_at  > NOW()
    </sql>

    <!-- GROUP BY + 집계 SELECT 절 -->
    <sql id="storeAggSelect">
        s.id,
        s.name,
        s.lat,
        s.lng,
        s.category,
        TIME_FORMAT(s.close_time, '%H:%i')  AS close_time,
        s.thumbnail_url,
        SUM(i.stock)                        AS total_stock,
        MIN(i.discount_price)               AS min_discount_price,
        MIN(i.original_price)               AS min_original_price,
        MAX(i.discount_rate)                AS max_discount_rate
    </sql>

    <!-- [요구사항 2] 새 가게 등록 후 캐시 무효화를 위한 Haversine 반경 조건 SQL 조각 -->
    <sql id="radiusCondition">
        <if test="centerLat != null and centerLng != null and radius != null">
            AND (6371 * ACOS(
                    COS(RADIANS(#{centerLat})) * COS(RADIANS(s.lat)) *
                    COS(RADIANS(s.lng) - RADIANS(#{centerLng})) +
                    SIN(RADIANS(#{centerLat})) * SIN(RADIANS(s.lat))
                 )) &lt;= #{radius}
        </if>
    </sql>


    <!-- ══════════════════════════════════════════════════════════════
         FR-M01 / FR-M02  마감 할인 가게 핀 전체 조회 (캐시 대상)
    ══════════════════════════════════════════════════════════════ -->
    <select id="findStorePins" resultMap="StoreMapDtoResultMap">
        SELECT
            <include refid="storeAggSelect"/>,
            <include refid="distanceCalc"/>
        FROM stores s
        INNER JOIN items i ON i.store_id = s.id
        WHERE
            <include refid="baseActiveCondition"/>
            <!-- 반경 필터: centerLat/centerLng/radius 모두 있을 때만 적용 -->
            <include refid="radiusCondition"/>
        GROUP BY
            s.id, s.name, s.lat, s.lng, s.category, s.close_time, s.thumbnail_url
        ORDER BY
            total_stock ASC,
            min_discount_price ASC
    </select>


    <!-- ══════════════════════════════════════════════════════════════
         [요구사항 4] 지도 이동 시 현재 뷰포트(Bbox) 내 가게 핀 조회
         SW(minLat,minLng) ~ NE(maxLat,maxLng) 사각형 범위 내 가게 반환.
         캐시 미적용 - 지도 moveend 이벤트마다 실시간 조회.
    ══════════════════════════════════════════════════════════════ -->
	 <select id="findStorePinsByBboxFiltered" resultMap="StoreMapDtoResultMap">
	    SELECT
	        s.id,
	        s.name,
	        s.lat,
	        s.lng,
	        s.category,
	        TIME_FORMAT(s.close_time, '%H:%i') AS close_time,
	        s.thumbnail_url,
	        SUM(i.stock)          AS total_stock,
	        MIN(i.discount_price) AS min_discount_price,
	        MIN(i.original_price) AS min_original_price,
	        MAX(i.discount_rate)  AS max_discount_rate,
	        <choose>
	            <when test="f.centerLat != null and f.centerLng != null">
	                (6371 * ACOS(
	                    COS(RADIANS(#{f.centerLat})) * COS(RADIANS(s.lat)) *
	                    COS(RADIANS(s.lng) - RADIANS(#{f.centerLng})) +
	                    SIN(RADIANS(#{f.centerLat})) * SIN(RADIANS(s.lat))
	                ))
	            </when>
	            <otherwise>NULL</otherwise>
	        </choose>
	        AS distance_km
	    FROM stores s
	    INNER JOIN items i ON i.store_id = s.id
	    <where>
	        s.deleted_at IS NULL
	        AND i.deleted_at IS NULL
	        AND i.stock > 0
	        AND i.expire_at > NOW()
	
	        AND s.lat BETWEEN #{bbox.minLat} AND #{bbox.maxLat}
	        AND s.lng BETWEEN #{bbox.minLng} AND #{bbox.maxLng}
	
	        <if test="f.category != null and f.category != ''">
	            AND s.category = #{f.category}
	        </if>
	
	        <if test="f.minDiscountRate != null">
	            AND i.discount_rate >= #{f.minDiscountRate}
	        </if>
	
	        <if test="f.maxDiscountRate != null">
	            AND i.discount_rate &lt;= #{f.maxDiscountRate}
	        </if>
	
	        <if test="f.maxDiscountPrice != null">
	            AND i.discount_price &lt;= #{f.maxDiscountPrice}
	        </if>
	
	        <if test="f.expireWithinMinutes != null">
	            AND i.expire_at &lt;= DATE_ADD(NOW(), INTERVAL #{f.expireWithinMinutes} MINUTE)
	        </if>
	    </where>
	    GROUP BY
	        s.id, s.name, s.lat, s.lng, s.category, s.close_time, s.thumbnail_url
	    <choose>
	        <when test="f.sortBy == 'discountRate'">
	            ORDER BY max_discount_rate DESC, total_stock ASC
	        </when>
	        <when test="f.sortBy == 'distance' and f.centerLat != null and f.centerLng != null">
	            ORDER BY distance_km ASC, total_stock ASC
	        </when>
	        <otherwise>
	            ORDER BY total_stock ASC, min_discount_price ASC
	        </otherwise>
	    </choose>
	</select>

    <!-- ══════════════════════════════════════════════════════════════
         FR-M03  가게 상세 조회 (가게 기본 정보 + 집계)
    ══════════════════════════════════════════════════════════════ -->
    <select id="findStoreDetail" resultMap="StoreDetailDtoResultMap">
        SELECT
            s.id,
            s.name,
            s.category,
            s.address,
            s.lat,
            s.lng,
            TIME_FORMAT(s.open_time,  '%H:%i') AS open_time,
            TIME_FORMAT(s.close_time, '%H:%i') AS close_time,
            s.thumbnail_url,
            ROUND(AVG(r.rating), 1)            AS avg_rating,
            COUNT(DISTINCT r.id)               AS review_count,
            <!-- 즐겨찾기 여부: memberId가 null이면 항상 false -->
            <choose>
                <when test="memberId != null">
                    CASE WHEN f.id IS NOT NULL THEN TRUE ELSE FALSE END AS favorited
                </when>
                <otherwise>
                    FALSE AS favorited
                </otherwise>
            </choose>
        FROM stores s
        LEFT JOIN reviews  r ON r.store_id = s.id AND r.deleted_at IS NULL
        <if test="memberId != null">
            LEFT JOIN favorites f ON f.store_id = s.id AND f.member_id = #{memberId}
        </if>
        WHERE
            s.id         = #{storeId}
            AND s.deleted_at IS NULL
        GROUP BY s.id
    </select>

    <!-- FR-M03 보조: 가게 이미지 목록 -->
    <select id="findStoreImageUrls" resultType="String">
        SELECT image_url
        FROM   store_images
        WHERE  store_id = #{storeId}
        ORDER BY sort_order ASC
    </select>

    <!-- FR-M03 보조: 가게의 활성 상품 목록 -->
    <select id="findActiveItemsByStore" resultMap="ItemSummaryDtoResultMap">
        SELECT
            id,
            name,
            original_price,
            discount_price,
            discount_rate,
            stock,
            DATE_FORMAT(expire_at, '%Y-%m-%d %H:%i') AS expire_at,
            thumbnail_url
        FROM items
        WHERE
            store_id    = #{storeId}
            AND deleted_at IS NULL
            AND stock       > 0
            AND expire_at   > NOW()
        ORDER BY stock ASC, expire_at ASC
    </select>


    <!-- ══════════════════════════════════════════════════════════════
         [요구사항 3] 무한 스크롤 페이징 (radius 필터 추가)
         radius가 null이 아닌 경우 centerLat/Lng 기준 반경 내 가게만 조회.
    ══════════════════════════════════════════════════════════════ -->
	   <select id="findStoresByPageFiltered" resultMap="StoreMapDtoResultMap">
	    SELECT
	        <include refid="storeAggSelect"/>,
	        <choose>
	            <when test="f.centerLat != null and f.centerLng != null">
	                (6371 * ACOS(
	                    COS(RADIANS(#{f.centerLat})) * COS(RADIANS(s.lat)) *
	                    COS(RADIANS(s.lng) - RADIANS(#{f.centerLng})) +
	                    SIN(RADIANS(#{f.centerLat})) * SIN(RADIANS(s.lat))
	                ))
	            </when>
	            <otherwise>NULL</otherwise>
	        </choose>
	        AS distance_km
	    FROM stores s
	    INNER JOIN items i ON i.store_id = s.id
	    <where>
	        s.deleted_at IS NULL
	        AND i.deleted_at IS NULL
	        AND i.stock > 0
	        AND i.expire_at > NOW()
	
	        <if test="f.category != null and f.category != ''">
	            AND s.category = #{f.category}
	        </if>
	        <if test="f.minDiscountRate != null">
	            AND i.discount_rate >= #{f.minDiscountRate}
	        </if>
	        <if test="f.maxDiscountRate != null">
	            AND i.discount_rate &lt;= #{f.maxDiscountRate}
	        </if>
	        <if test="f.maxDiscountPrice != null">
	            AND i.discount_price &lt;= #{f.maxDiscountPrice}
	        </if>
	        <if test="f.expireWithinMinutes != null">
	            AND i.expire_at &lt;= DATE_ADD(NOW(), INTERVAL #{f.expireWithinMinutes} MINUTE)
	        </if>
	        <if test="f.centerLat != null and f.centerLng != null and f.radius != null">
	            AND (6371 * ACOS(
	                    COS(RADIANS(#{f.centerLat})) * COS(RADIANS(s.lat)) *
	                    COS(RADIANS(s.lng) - RADIANS(#{f.centerLng})) +
	                    SIN(RADIANS(#{f.centerLat})) * SIN(RADIANS(s.lat))
	                 )) &lt;= #{f.radius}
	        </if>
	    </where>
	    GROUP BY
	        s.id, s.name, s.lat, s.lng, s.category, s.close_time, s.thumbnail_url
	    <choose>
	        <when test="f.sortBy == 'discountRate'">
	            ORDER BY max_discount_rate DESC, total_stock ASC
	        </when>
	        <when test="f.sortBy == 'distance' and f.centerLat != null and f.centerLng != null">
	            ORDER BY distance_km ASC, total_stock ASC
	        </when>
	        <otherwise>
	            ORDER BY total_stock ASC, min_discount_price ASC
	        </otherwise>
	    </choose>
	    LIMIT #{limit}
	    OFFSET #{offset}
	</select>
	
	<select id="countActiveStoresFiltered" resultType="long">
	    SELECT COUNT(DISTINCT s.id)
	    FROM stores s
	    INNER JOIN items i ON i.store_id = s.id
	    <where>
	        s.deleted_at IS NULL
	        AND i.deleted_at IS NULL
	        AND i.stock > 0
	        AND i.expire_at > NOW()
	
	        <if test="f.category != null and f.category != ''">
	            AND s.category = #{f.category}
	        </if>
	        <if test="f.minDiscountRate != null">
	            AND i.discount_rate >= #{f.minDiscountRate}
	        </if>
	        <if test="f.maxDiscountRate != null">
	            AND i.discount_rate &lt;= #{f.maxDiscountRate}
	        </if>
	        <if test="f.maxDiscountPrice != null">
	            AND i.discount_price &lt;= #{f.maxDiscountPrice}
	        </if>
	        <if test="f.expireWithinMinutes != null">
	            AND i.expire_at &lt;= DATE_ADD(NOW(), INTERVAL #{f.expireWithinMinutes} MINUTE)
	        </if>
	        <if test="f.centerLat != null and f.centerLng != null and f.radius != null">
	            AND (6371 * ACOS(
	                    COS(RADIANS(#{f.centerLat})) * COS(RADIANS(s.lat)) *
	                    COS(RADIANS(s.lng) - RADIANS(#{f.centerLng})) +
	                    SIN(RADIANS(#{f.centerLat})) * SIN(RADIANS(s.lat))
	                 )) &lt;= #{f.radius}
	        </if>
	    </where>
	</select>
	

    <!-- ══════════════════════════════════════════════════════════════
         Favorites (즐겨찾기) 토글용 쿼리
    ══════════════════════════════════════════════════════════════ -->

    <!-- 해당 회원이 이 가게를 이미 즐겨찾기 했는지 여부 -->
    <select id="existsFavorite" resultType="boolean">
        SELECT EXISTS (
            SELECT 1
            FROM favorites
            WHERE member_id = #{memberId}
              AND store_id  = #{storeId}
        )
    </select>

    <!-- 즐겨찾기 등록 -->
    <insert id="insertFavorite">
        INSERT INTO favorites (member_id, store_id)
        VALUES (#{memberId}, #{storeId})
    </insert>

    <!-- 즐겨찾기 해제 -->
    <delete id="deleteFavorite">
        DELETE FROM favorites
        WHERE member_id = #{memberId}
          AND store_id  = #{storeId}
    </delete>
    
     <!-- 오너 전용 ResultMap: StoreEntity (snake_case → camelCase 매핑) -->
    <resultMap id="storeEntityResultMap" type="com.deushu.store.domain.StoreEntity">
        <id     property="id"             column="id"/>
        <result property="ownerId"        column="owner_id"/>
        <result property="name"           column="name"/>
        <result property="businessNumber" column="business_number"/>
        <result property="category"       column="category"/>
        <result property="address"        column="address"/>
        <result property="lat"            column="lat"/>
        <result property="lng"            column="lng"/>
        <result property="openTime"       column="open_time"/>
        <result property="closeTime"      column="close_time"/>
        <result property="thumbnailUrl"   column="thumbnail_url"/>
        <result property="info"           column="info"/>
        <result property="createdAt"      column="created_at"/>
        <result property="updatedAt"      column="updated_at"/>
        <result property="deletedAt"      column="deleted_at"/>
        <result property="lastName"  column="last_name"/>
		<result property="firstName" column="first_name"/>
    </resultMap>

    <!-- store_images ResultMap -->
    <resultMap id="storeImageResultMap" type="com.deushu.store.dto.StoreImageDto">
        <id     property="id"        column="id"/>
        <result property="storeId"   column="store_id"/>
        <result property="imageUrl"  column="image_url"/>
        <result property="sortOrder" column="sort_order"/>
        <result property="createdAt" column="created_at"/>
    </resultMap>

    <!-- ── 오너 가게 조회 ─────────────────────────────────────────── -->

    <!-- 오너 ID로 가게 조회 (논리삭제 제외, 최신 1건) -->
    <select id="findByOwnerId" parameterType="long" resultMap="storeEntityResultMap">
        SELECT id, owner_id, name, business_number, category,
               address, lat, lng, open_time, close_time,
               thumbnail_url, info, created_at, updated_at, deleted_at
        FROM stores
        WHERE owner_id  = #{ownerId}
          AND deleted_at IS NULL
        ORDER BY created_at DESC
        LIMIT 1
    </select>

    <!-- 가게 ID로 단건 조회 (오너용) -->
    <select id="findStoreById" parameterType="long" resultMap="storeEntityResultMap">
        SELECT id, owner_id, name, business_number, category,
               address, lat, lng, open_time, close_time,
               thumbnail_url, info, created_at, updated_at, deleted_at
        FROM stores
        WHERE id        = #{storeId}
          AND deleted_at IS NULL
    </select>

    <!-- ── 가게 등록 / 수정 / 삭제 ───────────────────────────────── -->

    <!-- 기존 insertStore + update 두 쿼리 삭제하고 아래 하나로 교체 -->
	<insert id="upsertStore" parameterType="com.deushu.store.domain.StoreEntity"
	        useGeneratedKeys="true" keyProperty="id">
	    INSERT INTO stores (owner_id, name, business_number, category,
	                        address, lat, lng, open_time, close_time,
	                        thumbnail_url, info)
	    VALUES (#{ownerId}, #{name}, #{businessNumber}, #{category},
	            #{address}, #{lat}, #{lng}, #{openTime}, #{closeTime},
	            #{thumbnailUrl}, #{info})
	    ON DUPLICATE KEY UPDATE
	        name          = VALUES(name),
	        category      = VALUES(category),
	        address       = VALUES(address),
	        lat           = VALUES(lat),
	        lng           = VALUES(lng),
	        open_time     = VALUES(open_time),
	        close_time    = VALUES(close_time),
	        thumbnail_url = VALUES(thumbnail_url),
	        info          = VALUES(info),
	        updated_at    = NOW()
	</insert>

    <!-- 주소·위경도만 단독 업데이트 (다른 컬럼 보호) -->
    <update id="updateAddress" parameterType="com.deushu.store.domain.StoreEntity">
        UPDATE stores
        SET address    = #{address},
            lat        = #{lat},
            lng        = #{lng},
            updated_at = NOW()
        WHERE id       = #{id}
          AND owner_id = #{ownerId}
          AND deleted_at IS NULL
    </update>

    <!-- 가게 논리삭제 (폐업 처리) -->
    <update id="delete" parameterType="long">
        UPDATE stores
        SET deleted_at = NOW()
        WHERE id = #{storeId}
    </update>

    <!-- ── store_images 관리 ──────────────────────────────────────── -->

    <!-- 가게 추가 사진 목록 (sort_order 오름차순) -->
    <select id="findImagesByStoreId" parameterType="long" resultMap="storeImageResultMap">
        SELECT id, store_id, image_url, sort_order, created_at
        FROM store_images
        WHERE store_id = #{storeId}
        ORDER BY sort_order ASC
    </select>

    <!-- 가게 사진 추가 -->
    <insert id="insertImage" parameterType="com.deushu.store.dto.StoreImageDto"
            useGeneratedKeys="true" keyProperty="id">
        INSERT INTO store_images (store_id, image_url, sort_order)
        VALUES (#{storeId}, #{imageUrl}, #{sortOrder})
    </insert>

    <!-- 가게 사진 삭제 (storeId 조건으로 타 가게 이미지 삭제 방지) -->
    <delete id="deleteImage">
        DELETE FROM store_images
        WHERE id       = #{imageId}
          AND store_id = #{storeId}
    </delete>


    <!-- ── mock_business_registry 조회 ───────────────────────────── -->

    <!-- 사업자번호로 주소 + 위경도 조회 (오너 회원가입 검증 + 주소·위경도 자동입력) -->
    <!-- 사업자번호로 주소 조회 (위경도는 Nominatim 으로 별도 처리) -->
    <select id="findBusinessByNumber" parameterType="String" resultMap="storeEntityResultMap">
        SELECT business_number,
               store_name  AS name,
               address,
               last_name,
               first_name
        FROM mock_business_registry
        WHERE business_number = #{businessNumber}
          AND status          = 'ACTIVE'
    </select>
    
    
</mapper>